databird/__init__.py
databird/base_driver.py
databird/classes.py
databird/cli.py
databird/configuration.py
databird/dtutil.py
databird/queue.py
databird/runner.py
databird/utils.py
databird/webmonitor.py
databird_drivers/standard/__init__.py
databird_drivers/standard/command.py
databird_drivers/standard/filesystem.py
databird_drivers/standard/ftp.py
databird-0.7.1.dist-info/LICENSE.txt
databird-0.7.1.dist-info/METADATA
databird-0.7.1.dist-info/WHEEL
databird-0.7.1.dist-info/entry_points.txt
databird-0.7.1.dist-info/top_level.txt
databird-0.7.1.dist-info/RECORD
