Metadata-Version: 2.1
Name: databird
Version: 0.7.1
Summary: Keeps a local data repository up to date with different remote data sources.
Home-page: https://github.com/jonas-hagen/databird
Author: Jonas Hagen
Author-email: jonas.hagen@iap.unibe.ch
Maintainer: Jonas Hagen
Maintainer-email: jonas.hagen@iap.unibe.ch
License: MIT
Download-URL: https://github.com/jonas-hagen/databird/archive/databird-0.7.1.tar.gz
Platform: UNKNOWN
Classifier: Operating System :: OS Independent
Requires-Python: >=3.5.*, <4
Requires-Dist: click
Requires-Dist: dict-recursive-update
Requires-Dist: flask
Requires-Dist: frozendict
Requires-Dist: mr.bob
Requires-Dist: redis
Requires-Dist: rq
Requires-Dist: rq-dashboard
Requires-Dist: ruamel.yaml
